[
  {
    "name": "ENG-TSA - SecViz - Tanium Client Health - Tanium Prod EMEA to ServiceNow Prod",
    "description": "For export to ServiceNow as part of Tanium Client Health Visibility",
    "minimumPassPercentage": 80,
    "logLevel": 30,
    "schedule": "35 5,11,17,23 * * *",
    "scheduleTimeZone": "UTC",
    "moduleCallbackUri": null,
    "maxOldSpaceSize": 1,
    "streams": [
      {
        "route": "/v1/sources/pluginConfigurations/asset/report-source",
        "arguments": {
          "config": {
            "type": "Asset Computers",
            "maxTries": 5,
            "retryDelayMillis": 10000,
            "batchSize": 1000,
            "assetViewName": "ENG-TSA - SecViz - Tanium Client Health",
            "assetViewId": 4
          },
          "module": "asset",
          "plugin": "report-source",
          "type": "sources",
          "destinationType": "pluginConfigurations",
          "name": "asset-report-source-1617320909550-35"
        }
      },
      {
        "route": "/v1/formats/columns",
        "arguments": {
          "columns": [
            {
              "name": "id",
              "renameTo": "id",
              "type": null,
              "value": null,
              "hint": null,
              "valueType": "Numeric",
              "defaultValue": null,
              "formatString": null,
              "checked": false
            },
            {
              "name": "godaddy_serial",
              "renameTo": "GoDaddy Serial",
              "type": null,
              "value": null,
              "hint": null,
              "valueType": "Unmodified",
              "defaultValue": null,
              "formatString": null,
              "checked": true
            },
            {
              "name": "tanium_client_version",
              "renameTo": "Tanium Client Version",
              "type": null,
              "value": null,
              "hint": null,
              "valueType": "Unmodified",
              "defaultValue": null,
              "formatString": null,
              "checked": true
            },
            {
              "name": "tanium_client_core_health",
              "renameTo": "Tanium Client Core Health",
              "type": null,
              "value": null,
              "hint": null,
              "valueType": "Unmodified",
              "defaultValue": null,
              "formatString": null,
              "checked": true
            },
            {
              "name": "patch_coverage_status",
              "renameTo": "Tanium Patch Coverage Status",
              "type": null,
              "value": null,
              "hint": null,
              "valueType": "Unmodified",
              "defaultValue": null,
              "formatString": null,
              "checked": true
            },
            {
              "name": "patch_is_process_running",
              "renameTo": "Tanium Patch Service Running",
              "type": null,
              "value": null,
              "hint": null,
              "valueType": "Unmodified",
              "defaultValue": null,
              "formatString": null,
              "checked": true
            },
            {
              "name": "updated_at",
              "renameTo": "Tanium Asset Record Updated",
              "type": null,
              "value": null,
              "hint": null,
              "valueType": "Unmodified",
              "defaultValue": null,
              "formatString": null,
              "checked": true
            },
            {
              "name": "created_at",
              "renameTo": "Tanium Asset Record Created",
              "type": null,
              "value": null,
              "hint": null,
              "valueType": "Unmodified",
              "defaultValue": null,
              "formatString": null,
              "checked": true
            }
          ]
        }
      },
      {
        "route": "/v1/formats/csvs",
        "arguments": {
          "includeHeaders": true,
          "detectDde": true,
          "valueEscape": "",
          "valueEscapeReplace": ""
        }
      },
      {
        "route": "/v1/destinations/https",
        "arguments": {
          "headers": [
            {
              "name": "Accept",
              "value": "application/json"
            },
            {
              "name": "Content-Type",
              "value": "text/csv"
            }
          ],
          "name": "ENG-TSA - SecViz - Tanium Client Health - Tanium Prod EMEA to ServiceNow Prod",
          "destinationType": "https",
          "url": "https://godaddy.service-now.com/api/now/attachment/file?table_name=u_temp_upload&table_sys_id=e7e8ec04db1f6c5459ac6e25ca961986&file_name=tanium-client-health-emea.csv",
          "method": "POST",
          "useAuthentication": true,
          "username": "tanium",
          "useProxy": false,
          "connectionTimeout": 600,
          "batchSize": 0,
          "secure": true,
          "trustOnFirstUse": true,
          "cert": "",
          "password": "[not available on export]"
        }
      }
    ],
    "destinationType": "https"
  }
]